_pyvpmr.cpython-310-darwin.so
pyvpmr/__init__.py
pyvpmr/.dylibs/libstdc++.6.dylib
pyvpmr/.dylibs/libtbb.12.17.dylib
pyvpmr/.dylibs/libgcc_s.1.1.dylib
pyvpmr/.dylibs/libgmp.10.dylib
pyvpmr/.dylibs/libmpfr.6.dylib
pyvpmr-260115.dist-info/RECORD
pyvpmr-260115.dist-info/WHEEL
pyvpmr-260115.dist-info/top_level.txt
pyvpmr-260115.dist-info/METADATA
pyvpmr-260115.dist-info/licenses/LICENSE
