Metadata-Version: 2.4
Name: pyvpmr
Version: 260115
Summary: The VPMR Algorithm
Author-email: Theodore Chang <tlcfem@gmail.com>
Maintainer-email: Theodore Chang <tlcfem@gmail.com>
License:                     GNU GENERAL PUBLIC LICENSE
Project-URL: Homepage, https://github.com/TLCFEM/vpmr
Project-URL: Bug Reports, https://github.com/TLCFEM/vpmr/issuess
Project-URL: Source, https://github.com/TLCFEM/vpmr
Keywords: vpmr,kernel function,convolution
Classifier: Development Status :: 5 - Production/Stable
Classifier: Intended Audience :: Education
Classifier: Intended Audience :: Science/Research
Classifier: Topic :: Scientific/Engineering
Classifier: Programming Language :: Python :: 3
Classifier: Programming Language :: Python :: 3.8
Classifier: Programming Language :: Python :: 3.9
Classifier: Programming Language :: Python :: 3.10
Classifier: Programming Language :: Python :: 3.11
Classifier: Programming Language :: Python :: 3.12
Classifier: Programming Language :: Python :: 3.13
Classifier: Programming Language :: Python :: 3.14
Classifier: Programming Language :: Python :: 3 :: Only
Requires-Python: >=3.8
License-File: LICENSE
Requires-Dist: numpy
Requires-Dist: matplotlib
Dynamic: description
Dynamic: description-content-type
Dynamic: license-file
